setup.cfg
setup.py
class_file/_init_.py
class_file.egg-info/PKG-INFO
class_file.egg-info/SOURCES.txt
class_file.egg-info/dependency_links.txt
class_file.egg-info/not-zip-safe
class_file.egg-info/top_level.txt