Metadata-Version: 2.1
Name: class-file
Version: 0.1
Summary: удобный класс дял работы с файлом
Author-email: nikolajh913@gmail.com
